{
  "_id": "940370901",
  "_thread": "1430919233",
  "_parent": null,
  "name": "mrb",
  "email": "mrb@hsdev.com",
  "message": "<p>Turns out i could do the other side as well, because i've taken the shimming a bit out of the actual middle. The brake-pads position is not centered the same as the center of the brake calliper. Taking the shimming a bit out of the middle makes it a bit easier to fit the brake pads. For all intents and purpose the discs are in the middle :-)</p>",
  "date": "2008-11-02T20:49:43Z",
  "ip": "212.61.102.6",
  "spam": "false",
  "deleted": "false"
}
