{"_id":"81e2c8b0-6323-11ea-8cb5-6915dcf0bdb7","_parent":"ID of parent message","name":"JudyDaync","email":"nina@mail.com","message":"<a href=\"https://lasix.us.com/\">lasix for sale</a> <a href=\"https://sildalis365.us.com/\">discount sildalis</a> <a href=\"https://anafranil.us.com/\">anafranil 25mg</a> <a href=\"https://buycelexa.us.com/\">celexa 20mg</a> <a href=\"https://propranolol.us.com/\">propranolol hcl</a> <a href=\"https://viagrabest.us.com/\">viagra prescription</a>","date":1583881474}